saturnfs/__init__.py
saturnfs/_version.py
saturnfs/errors.py
saturnfs/settings.py
saturnfs/utils.py
saturnfs/api/__init__.py
saturnfs/api/base.py
saturnfs/api/delete.py
saturnfs/api/download.py
saturnfs/api/list.py
saturnfs/api/upload.py
saturnfs/api/usage.py
saturnfs/cli/__init__.py
saturnfs/cli/callback.py
saturnfs/cli/commands.py
saturnfs/cli/main.py
saturnfs/cli/utils.py
saturnfs/client/__init__.py
saturnfs/client/aws.py
saturnfs/client/file_transfer.py
saturnfs/client/object_storage.py
saturnfs/client/saturnfs.py
saturnfs/schemas/__init__.py
saturnfs/schemas/base.py
saturnfs/schemas/delete.py
saturnfs/schemas/download.py
saturnfs/schemas/list.py
saturnfs/schemas/reference.py
saturnfs/schemas/upload.py
saturnfs/schemas/usage.py
saturnfs-2024.3.28.dist-info/METADATA
saturnfs-2024.3.28.dist-info/WHEEL
saturnfs-2024.3.28.dist-info/entry_points.txt
saturnfs-2024.3.28.dist-info/top_level.txt
saturnfs-2024.3.28.dist-info/RECORD
